<?xml version="1.0"?>
<Script>
  <Name>
    <lcid127>Disable Timeline</lcid127>
    <lcid12>Désactiver la chronologie</lcid12>
  </Name>
  <Description>
    <lcid127>Timeline allows users to review their activity history and quickly return to their previous tasks.</lcid127>
    <lcid12>La chronologie permet aux utilisateurs de revoir l'historique de leur activité et de retourner rapidement à leurs taches précédentes.</lcid12>
  </Description>
  <Category>Customization</Category>
  <Advised>Limited</Advised>
  <Host>Regedit</Host>
  <Impact>Ergonomics</Impact>
  <Code>Windows Registry Editor Version 5.00

[HKEY_LOCAL_MACHINE\SOFTWARE\Policies\Microsoft\Windows\System]
"EnableActivityFeed"=dword:00000000</Code>
</Script>